{
  "type": "minecraft:entity",
  "pools": [
    {
      "rolls": {
        "min": 14.0,
        "max": 16.0,
        "type": "minecraft:uniform"
      },
      "bonus_rolls": {
        "min": 0.0,
        "max": 1.0,
        "type": "minecraft:uniform"
      },
      "entries": [
        {
          "type": "minecraft:item",
          "weight": 3,
          "quality": 1,
          "functions": [
            {
              "function": "minecraft:set_count",
              "count": {
                "min": 1.0,
                "max": 1.0,
                "type": "minecraft:uniform"
              }
            }
          ],
          "name": "minecraft:experience_bottle"
        }
      ]
    },
    {
      "rolls": {
        "min": 4.0,
        "max": 6.0,
        "type": "minecraft:uniform"
      },
      "bonus_rolls": {
        "min": 0.0,
        "max": 1.0,
        "type": "minecraft:uniform"
      },
      "conditions": [
        {
          "condition": "minecraft:killed_by_player"
        }
      ],
      "entries": [
        {
          "type": "minecraft:loot_table",
          "weight": 400,
          "quality": 1,
          "value": "rpgloot:rare_items"
        },
        {
          "type": "minecraft:loot_table",
          "weight": 100,
          "quality": 3,
          "value": "rpgloot:veryrare_items"
        },
        {
          "type": "minecraft:loot_table",
          "weight": 10,
          "quality": 5,
          "value": "rpgloot:legendary_items"
        },
        {
          "type": "minecraft:item",
          "name": "minecraft:leather_chestplate",
          "weight": 1,
          "quality": 5,
          "functions": [
            {
              "function": "minecraft:set_attributes",
              "modifiers": [
                {
                  "name": "armor",
                  "attribute": "minecraft:armor",
                  "operation": "add_value",
                  "slot": "chest",
                  "amount": {
                    "min": 4.6,
                    "max": 6.5,
                    "type": "minecraft:uniform"
                  },
                  "id": "rpgloot:armor_mod"
                },
                {
                  "name": "movementspeed",
                  "attribute": "minecraft:movement_speed",
                  "operation": "add_multiplied_base",
                  "slot": "chest",
                  "amount": {
                    "min": 0.05,
                    "max": 0.25,
                    "type": "minecraft:uniform"
                  },
                  "id": "rpgloot:movement_speed_mod"
                },
                {
                  "name": "maxhealth",
                  "attribute": "minecraft:max_health",
                  "operation": "add_value",
                  "slot": "chest",
                  "amount": {
                    "min": 0.0,
                    "max": 4.0,
                    "type": "minecraft:uniform"
                  },
                  "id": "rpgloot:max_health_mod"
                },
                {
                  "name": "attackdamage",
                  "attribute": "minecraft:attack_damage",
                  "operation": "add_value",
                  "slot": "chest",
                  "amount": {
                    "min": 0.0,
                    "max": 2.0,
                    "type": "minecraft:uniform"
                  },
                  "id": "rpgloot:attack_damage_mod"
                },
                {
                  "name": "attackspeed",
                  "attribute": "minecraft:attack_speed",
                  "operation": "add_value",
                  "slot": "chest",
                  "amount": {
                    "min": 0.0,
                    "max": 0.2,
                    "type": "minecraft:uniform"
                  },
                  "id": "rpgloot:attack_speed_mod"
                },
                {
                  "name": "luck",
                  "attribute": "minecraft:luck",
                  "operation": "add_value",
                  "slot": "chest",
                  "amount": {
                    "min": 0.0,
                    "max": 0.5,
                    "type": "minecraft:uniform"
                  },
                  "id": "rpgloot:luck_mod"
                }
              ]
            },
            {
              "function": "minecraft:set_lore",
              "mode": "replace_all",
              "lore": [
                {
                  "text": ""
                },
                {
                  "text": "Legendary",
                  "italic": "false",
                  "color": "gold"
                },
                {
                  "text": "Stop, drop, and roll.",
                  "italic": "true",
                  "color": "gray"
                }
              ]
            },
            {
              "function": "minecraft:set_name",
              "name": {
                "text": "Aegis of Flame",
                "color": "gold"
              }
            },
            {
              "function": "minecraft:set_components",
              "components": {
                "minecraft:unbreakable": {}
              }
            },
            {
              "function": "minecraft:set_custom_data",
              "tag": "{Age:-32768}"
            },
            {
              "function": "minecraft:set_components",
              "components": {
                "minecraft:dyed_color": {
                  "rgb": 16741376,
                  "show_in_tooltip": true
                }
              }
            },
            {
              "function": "minecraft:set_components",
              "components": {
                "minecraft:enchantments": {
                  "levels": {
                    "minecraft:fire_protection": 10
                  }
                }
              }
            },
            {
              "function": "minecraft:set_custom_data",
              "tag": "{lvl:10}"
            },
            {
              "function": "enchant_with_levels",
              "treasure": true,
              "levels": {
                "min": 45,
                "max": 64,
                "type": "minecraft:uniform"
              }
            }
          ]
        },
        {
          "type": "minecraft:item",
          "name": "minecraft:golden_axe",
          "weight": 1,
          "quality": 5,
          "functions": [
            {
              "function": "minecraft:set_attributes",
              "modifiers": [
                {
                  "name": "damage",
                  "attribute": "minecraft:attack_damage",
                  "operation": "add_value",
                  "slot": "mainhand",
                  "amount": {
                    "min": 9.0,
                    "max": 13.0,
                    "type": "minecraft:uniform"
                  },
                  "id": "rpgloot:attack_damage_mod"
                },
                {
                  "name": "attackSpeed",
                  "attribute": "minecraft:attack_speed",
                  "operation": "add_value",
                  "slot": "mainhand",
                  "amount": {
                    "min": -2.4,
                    "max": -2.0,
                    "type": "minecraft:uniform"
                  },
                  "id": "rpgloot:attack_speed_mod"
                }
              ]
            },
            {
              "function": "minecraft:set_lore",
              "mode": "replace_all",
              "lore": [
                {
                  "text": ""
                },
                {
                  "text": "Legendary",
                  "italic": "false",
                  "color": "gold"
                },
                {
                  "text": "Shining. Shimmering. Splendid.",
                  "italic": "true",
                  "color": "yellow"
                }
              ]
            },
            {
              "function": "minecraft:set_name",
              "name": {
                "text": "Radiance",
                "color": "yellow"
              }
            },
            {
              "function": "minecraft:set_components",
              "components": {
                "minecraft:unbreakable": {}
              }
            },
            {
              "function": "minecraft:set_custom_data",
              "tag": "{Age:-32768}"
            },
            {
              "function": "minecraft:set_components",
              "components": {
                "minecraft:enchantments": {
                  "levels": {
                    "minecraft:fire_aspect": 5
                  }
                }
              }
            },
            {
              "function": "minecraft:set_custom_data",
              "tag": "{lvl:5}"
            },
            {
              "function": "enchant_with_levels",
              "treasure": true,
              "levels": {
                "min": 64,
                "max": 64,
                "type": "minecraft:uniform"
              }
            }
          ]
        }
      ]
    }
  ]
}