{
  "type": "minecraft:entity",
  "pools": [
    {
      "rolls": 1,
      "entries": [
        {
          "type": "minecraft:item",
          "name": "minecraft:diamond_sword",
          "functions": [
            {
              "function": "minecraft:set_name",
              "name": {"text": "[DEBUG] Legendary Test Drop - Bat Kill Confirmed!", "color": "gold", "bold": true}
            },
            {
              "function": "minecraft:set_enchantments",
              "enchantments": {
                "minecraft:sharpness": 5,
                "minecraft:unbreaking": 3,
                "minecraft:looting": 3
              }
            }
          ]
        }
      ]
    }
  ]
}
